{
    "name": "TaManoeuvre",
    "package_name": "ta_manoeuvre",
    "description": "then take a step right so you're standing in front of the light.",
    "id": 1,
    "effect": "synchronous",
    "input_parameters": {
        "direction": {
            "pvf_type": "string",
            "pvf_example": "right"
        },
        "distance": {
            "amount": {
                "pvf_type": "number",
                "pvf_example": "step"
            },
            "unit": {
                "pvf_type": "string",
                "pvf_example": "a"
            }
        },
        "extent": {
            "pvf_type": "string",
            "pvf_example": "so you're standing in front of the light"
        },
        "verb": {
            "pvf_type": "string",
            "pvf_example": "take"
        }
    },
    "parents": [
        {
            "name": "TaNavigation",
            "id": 0
        }
    ]
}